{
  "date": "2026-06-30",
  "universe": "S&P 500 Pre-Market Gappers",
  "strategy": "Gap Fade",
  "gate_rules": [
    "fade_risk = false required",
    "catalyst_type in [earnings_beat, partnership_contract, guidance, deal, spinoff]",
    "gap_pct >= 5%, premarket_vol >= 500K",
    "fade_risk=true types blocked: analyst_action, ma_rumor, dilution_offering, no_clear_catalyst, other"
  ],
  "note": "First full day running fade_risk gate after backtest switch (2026-06-29). Gate filtered 7/8 candidates.",
  "candidates": [
    {
      "symbol": "FCEL",
      "gap_pct": 24.17,
      "premarket_volume": 20998917,
      "float_m": 67.44,
      "float_rotation_pct": 31.14,
      "gap_vs_atr": 1.91,
      "catalyst_type": "analyst_action",
      "catalyst_summary": "Analyst upgrade of FuelCell Energy; no new fundamental business catalyst cited.",
      "fade_risk": true,
      "decision": "SKIP",
      "skip_reason": "fade_risk: analyst_action",
      "trade": null
    },
    {
      "symbol": "VSAT",
      "gap_pct": 23.79,
      "premarket_volume": 4637701,
      "float_m": 127.69,
      "float_rotation_pct": 3.63,
      "gap_vs_atr": 3.12,
      "catalyst_type": "ma_rumor",
      "catalyst_summary": "Analyst calls Viasat 'last major satellite spectrum play' post Rocket Lab-Iridium deal, fueling acquisition speculation. Unconfirmed.",
      "fade_risk": true,
      "decision": "SKIP",
      "skip_reason": "fade_risk: ma_rumor",
      "trade": null
    },
    {
      "symbol": "OC",
      "gap_pct": 15.26,
      "premarket_volume": 4903716,
      "float_m": 79.63,
      "float_rotation_pct": 6.16,
      "gap_vs_atr": 3.35,
      "catalyst_type": "ma_rumor",
      "catalyst_summary": "Unsolicited takeover approach from Carlisle reported; no deal confirmed.",
      "fade_risk": true,
      "decision": "SKIP",
      "skip_reason": "fade_risk: ma_rumor",
      "trade": null
    },
    {
      "symbol": "MSTR",
      "gap_pct": 12.6,
      "premarket_volume": 43453442,
      "float_m": 329.95,
      "float_rotation_pct": 13.17,
      "gap_vs_atr": 1.21,
      "catalyst_type": "other",
      "catalyst_summary": "Reports suggest Strategy may sell Bitcoin as funding model faces pressure. Headlines do not explain the move clearly.",
      "fade_risk": true,
      "decision": "SKIP",
      "skip_reason": "fade_risk: other (unclear catalyst)",
      "trade": null
    },
    {
      "symbol": "FBIN",
      "gap_pct": 10.9,
      "premarket_volume": 6723271,
      "float_m": 116.55,
      "float_rotation_pct": 5.77,
      "gap_vs_atr": 2.39,
      "catalyst_type": "other",
      "catalyst_summary": "New CEO appointment announced.",
      "fade_risk": true,
      "decision": "SKIP",
      "skip_reason": "fade_risk: other (mgmt change)",
      "trade": null
    },
    {
      "symbol": "CHTR",
      "gap_pct": 9.38,
      "premarket_volume": 12644049,
      "float_m": 80.45,
      "float_rotation_pct": 15.72,
      "gap_vs_atr": 1.73,
      "catalyst_type": "partnership_contract",
      "catalyst_summary": "Charter Communications gained on SpaceX partnership deal news.",
      "fade_risk": false,
      "decision": "TRADE",
      "skip_reason": null,
      "trade": {
        "direction": "long",
        "entry": 140.22,
        "stop": 138.44,
        "target": 143.79,
        "qty": 7,
        "risk_per_share": 1.78,
        "reward_per_share": 3.57,
        "rr_ratio": 2.0,
        "order_id": "e7ac3d3b-457b-4547-b407-f0873de92083",
        "exit_price": null,
        "exit_time": null,
        "pnl": null,
        "status": "open"
      }
    },
    {
      "symbol": "LBRDA",
      "gap_pct": 9.33,
      "premarket_volume": 500109,
      "float_m": 16.99,
      "float_rotation_pct": 2.94,
      "gap_vs_atr": 2.02,
      "catalyst_type": "no_clear_catalyst",
      "catalyst_summary": "No concrete catalyst identified; generic technical analysis content in headlines.",
      "fade_risk": true,
      "decision": "SKIP",
      "skip_reason": "fade_risk: no_clear_catalyst",
      "trade": null
    },
    {
      "symbol": "PTRN",
      "gap_pct": 6.77,
      "premarket_volume": 4002452,
      "float_m": 50.55,
      "float_rotation_pct": 7.92,
      "gap_vs_atr": 1.24,
      "catalyst_type": "dilution_offering",
      "catalyst_summary": "Secondary stock offering launched; Goldman Sachs raised PT on AI-launch news partially offset the dilution pressure.",
      "fade_risk": true,
      "decision": "SKIP",
      "skip_reason": "fade_risk: dilution_offering",
      "trade": null
    }
  ]
}
